yield_analysis_sdk/__init__.py
yield_analysis_sdk/analysis.py
yield_analysis_sdk/exceptions.py
yield_analysis_sdk/subgraph.py
yield_analysis_sdk/type.py
yield_analysis_sdk/validators.py
yield_analysis_sdk-0.5.5.dist-info/METADATA
yield_analysis_sdk-0.5.5.dist-info/WHEEL
yield_analysis_sdk-0.5.5.dist-info/entry_points.txt
yield_analysis_sdk-0.5.5.dist-info/RECORD
