Metadata-Version: 2.4
Name: yield-analysis-sdk
Version: 0.5.5
Summary: A Python SDK for analyzing DeFi vault performance and yield metrics
Project-URL: Homepage, https://github.com/Logarithm-Labs/yield-analysis-sdk
Project-URL: Documentation, https://yield-analysis-sdk.readthedocs.io/
Project-URL: Repository, https://github.com/Logarithm-Labs/yield-analysis-sdk
Project-URL: Issues, https://github.com/Logarithm-Labs/yield-analysis-sdk/issues
Author-email: Tal <talcrypto@logarithm.fi>
License: MIT
Keywords: AI,analysis,defi,yield
Requires-Python: >=3.10
Requires-Dist: pydantic>=2.5.0
Requires-Dist: requests>=2.25.0
